jsonvalidate/__init__.py
jsonvalidate/_mock.py
jsonvalidate/jsonvalidate.py
jsonvalidate-0.1.7.dist-info/DESCRIPTION.rst
jsonvalidate-0.1.7.dist-info/METADATA
jsonvalidate-0.1.7.dist-info/RECORD
jsonvalidate-0.1.7.dist-info/WHEEL
jsonvalidate-0.1.7.dist-info/metadata.json
jsonvalidate-0.1.7.dist-info/top_level.txt
