Metadata-Version: 2.0
Name: jsonvalidate
Version: 0.1.7
Summary: JSON validation Schema
Home-page: https://github.com/robusgauli/jsonvalidate
Author: Robus Gauli
Author-email: robusgauli@gmail.com
License: MIT license
Keywords: jsonvalidate
Platform: UNKNOWN
Classifier: Development Status :: 2 - Pre-Alpha
Classifier: Intended Audience :: Developers
Classifier: License :: OSI Approved :: MIT License
Classifier: Natural Language :: English
Classifier: Programming Language :: Python :: 2
Classifier: Programming Language :: Python :: 2.7
Classifier: Programming Language :: Python :: 3
Classifier: Programming Language :: Python :: 3.4
Classifier: Programming Language :: Python :: 3.5
Classifier: Programming Language :: Python :: 3.6
Requires-Dist: six
